D2AF/Calculator.py
D2AF/Combine_fig_MS.py
D2AF/Combine_fig_ppt.py
D2AF/Combine_method_SI.py
D2AF/Combine_multi_conf.py
D2AF/Molecule.py
D2AF/Results.py
D2AF/Strain_energy.py
D2AF/__init__.py
D2AF/atompair.py
D2AF/autofragment.py
D2AF/basis_functions.py
D2AF/fragmentation.py
D2AF/inputs.py
D2AF/multi_mov.py
D2AF/pml_str.py
D2AF/write_run_pml.py
D2AF/lib/ONIOM_Cscale.txt
D2AF/lib/ONIOM_Hscale.txt
D2AF/lib/ONIOM_Nscale.txt
D2AF/lib/ONIOM_Oscale.txt
D2AF-1.1.4.dist-info/METADATA
D2AF-1.1.4.dist-info/WHEEL
D2AF-1.1.4.dist-info/entry_points.txt
D2AF-1.1.4.dist-info/top_level.txt
D2AF-1.1.4.dist-info/RECORD
