Metadata-Version: 2.1
Name: D2AF
Version: 1.1.4
Summary: Distortion Distribution Analysis enabled by Fragmentation
Home-page: https://github.com/yanjordan/D2AF
Author-email: yanzy@sustech.edu.cn
Requires-Python: ~=3.9
